nadfun_sdk/__init__.py
nadfun_sdk/constants.py
nadfun_sdk/token.py
nadfun_sdk/trade.py
nadfun_sdk/types.py
nadfun_sdk/utils.py
nadfun_sdk/abis/Router.json
nadfun_sdk/abis/curve.json
nadfun_sdk/abis/erc20Permit.json
nadfun_sdk/abis/lens.json
nadfun_sdk/abis/v3factory.json
nadfun_sdk/abis/v3pool.json
nadfun_sdk/stream/__init__.py
nadfun_sdk/stream/types.py
nadfun_sdk/stream/utils.py
nadfun_sdk/stream/curve/__init__.py
nadfun_sdk/stream/curve/indexer.py
nadfun_sdk/stream/curve/parser.py
nadfun_sdk/stream/curve/stream.py
nadfun_sdk/stream/dex/__init__.py
nadfun_sdk/stream/dex/indexer.py
nadfun_sdk/stream/dex/parser.py
nadfun_sdk/stream/dex/stream.py
nadfun_sdk-0.1.3.dist-info/licenses/LICENSE
nadfun_sdk-0.1.3.dist-info/METADATA
nadfun_sdk-0.1.3.dist-info/WHEEL
nadfun_sdk-0.1.3.dist-info/top_level.txt
nadfun_sdk-0.1.3.dist-info/RECORD
