Metadata-Version: 2.4
Name: nadfun-sdk
Version: 0.1.3
Summary: Python SDK for Nad.fun contracts
Author-email: Nadfun <dev@nad.fun>
License: MIT
Project-URL: Homepage, https://github.com/naddotfun/nadfun-sdk
Project-URL: Issues, https://github.com/naddotfun/nadfun-sdk/issues
Project-URL: Repository, https://github.com/naddotfun/nadfun-sdk
Keywords: blockchain,ethereum,defi,trading,bonding-curve
Classifier: Development Status :: 4 - Beta
Classifier: Intended Audience :: Developers
Classifier: License :: OSI Approved :: MIT License
Classifier: Programming Language :: Python :: 3
Classifier: Programming Language :: Python :: 3.11
Classifier: Programming Language :: Python :: 3.12
Classifier: Topic :: Software Development :: Libraries :: Python Modules
Requires-Python: >=3.11
License-File: LICENSE
Requires-Dist: web3>=6.0.0
Requires-Dist: eth-account>=0.10.0
Requires-Dist: eth-abi>=4.0.0
Requires-Dist: eth-utils>=2.0.0
Provides-Extra: dev
Requires-Dist: pytest>=7.0.0; extra == "dev"
Requires-Dist: pytest-asyncio>=0.21.0; extra == "dev"
Requires-Dist: black>=23.0.0; extra == "dev"
Requires-Dist: mypy>=1.0.0; extra == "dev"
Requires-Dist: python-dotenv>=1.0.0; extra == "dev"
Dynamic: license-file
